{
    "timeStamp": "1730343829",
    "tags": [
        {
            "name": "make" ,
            "value": "honda"
        },
        {
            "name": "model" ,
            "value": "fit"
        },
        {
            "name": "year" ,
            "value": "2007"
        }
    ],
    "fields": [
        {
            "name": "rpm" ,
            "type": "long",
            "value": 2000
        },
        {
            "name" : "throttlePos",
            "type": "float",
            "value": 0.2
        }
    ]
}
